bin/__init__.py
script/jenkinsfile-tala
tala/__init__.py
tala/config.py
tala/domain_orchestration.py
tala/event.py
tala/http_formatting.py
tala/cli/__init__.py
tala/cli/argument_parser.py
tala/cli/console_formatting.py
tala/cli/console_script.py
tala/cli/tdm/__init__.py
tala/cli/tdm/passivity_timer.py
tala/cli/tdm/tdm_cli.py
tala/cli/tdm/test/__init__.py
tala/cli/tdm/test/test_passivity_timer.py
tala/cli/tdm/test/test_tdm_cli.py
tala/ddd/__init__.py
tala/ddd/ddd_manager.py
tala/ddd/ddd_xml_compiler.py
tala/ddd/domain_manager.py
tala/ddd/extended_ddd.py
tala/ddd/files.py
tala/ddd/json_parser.py
tala/ddd/parser.py
tala/ddd/utils.py
tala/ddd/grammar/__init__.py
tala/ddd/grammar/parser.py
tala/ddd/grammar/reader.py
tala/ddd/grammar/test/__init__.py
tala/ddd/grammar/test/test_parser.py
tala/ddd/loading/__init__.py
tala/ddd/loading/ddd_loader.py
tala/ddd/loading/ddd_set_loader.py
tala/ddd/loading/extended_ddd_loader.py
tala/ddd/loading/extended_ddd_set_loader.py
tala/ddd/loading/python_module_loader.py
tala/ddd/loading/test/__init__.py
tala/ddd/loading/test/test_extended_ddd_loader.py
tala/ddd/loading/test/test_extended_ddd_set_loader.py
tala/ddd/maker/__init__.py
tala/ddd/maker/ddd_maker.py
tala/ddd/maker/utils.py
tala/ddd/maker/templates/domain_template.xml
tala/ddd/maker/templates/interaction_tests_sem_template.txt
tala/ddd/maker/templates/ontology_template.xml
tala/ddd/maker/templates/service_interface_template.xml
tala/ddd/maker/templates/word_list_template.txt
tala/ddd/maker/test/__init__.py
tala/ddd/maker/test/test_ddd_maker.py
tala/ddd/schemas/__init__.py
tala/ddd/schemas/domain.xsd
tala/ddd/schemas/ontology.xsd
tala/ddd/schemas/service_interface.xsd
tala/ddd/schemas/xs3p/LICENSE.html
tala/ddd/schemas/xs3p/xs3p.xsl
tala/ddd/services/__init__.py
tala/ddd/services/abstract_service_wrapper.py
tala/ddd/services/constants.py
tala/ddd/services/http.py
tala/ddd/services/service_interface.py
tala/ddd/services/parameters/__init__.py
tala/ddd/services/parameters/binding.py
tala-29.6.1.dist-info/METADATA
tala-29.6.1.dist-info/WHEEL
tala-29.6.1.dist-info/top_level.txt
tala-29.6.1.dist-info/RECORD
